aixstanzaparser.py
aixstanzaparser-1.1.0.dist-info/LICENSE
aixstanzaparser-1.1.0.dist-info/METADATA
aixstanzaparser-1.1.0.dist-info/WHEEL
aixstanzaparser-1.1.0.dist-info/RECORD
