Metadata-Version: 2.3
Name: aixstanzaparser
Version: 1.1.0
Summary: AIX stanza parser
License: Apache-2.0
Author: Dave Marquardt
Author-email: daverrtx@gmail.com
Maintainer: Dave Marquardt
Maintainer-email: daverrtx@gmail.com
Requires-Python: >=3.9
Classifier: Programming Language :: Python :: 3
Classifier: Operating System :: OS Independent
Requires-Dist: configparser (>=7.2.0,<8.0.0)
Project-URL: Homepage, https://github.com/davemq/aixstanzaparser
Project-URL: Issues, https://github.com/davemq/aixstanzaparser/issues
